karafs/__init__.py
karafs/__main__.py
karafs/karafs.py
karafs-0.1.1.data/scripts/karafs
karafs-0.1.1.dist-info/LICENSE
karafs-0.1.1.dist-info/METADATA
karafs-0.1.1.dist-info/WHEEL
karafs-0.1.1.dist-info/top_level.txt
karafs-0.1.1.dist-info/RECORD
