Metadata-Version: 2.1
Name: karafs
Version: 0.1.1
Summary: random funny persian name generator
Home-page: https://github.com/iamvee/karafs
Author: Vahid Naeini
Author-email: naeini.v@gmail.com
License: UNKNOWN
Platform: UNKNOWN
Classifier: Programming Language :: Python :: 3
Classifier: License :: OSI Approved :: MIT License
Classifier: Operating System :: OS Independent
Requires-Python: >=3.6
Requires-Dist: docutils (>=0.3)
